oliverr_py/__init__.py
oliverr_py/misc/__init__.py
oliverr_py/misc/temp.py
oliverr_py/pathfinding/A*.py
oliverr_py/pathfinding/Node.py
oliverr_py/pathfinding/__init__.py
oliverr_py-0.0.3.dist-info/LICENSE
oliverr_py-0.0.3.dist-info/METADATA
oliverr_py-0.0.3.dist-info/WHEEL
oliverr_py-0.0.3.dist-info/top_level.txt
oliverr_py-0.0.3.dist-info/RECORD
