Metadata-Version: 2.1
Name: oliverr-py
Version: 0.0.3
Summary: A collection of miscellaneous tools
Home-page: https://github.com/insert_url_here
Author: Oliver Rayner
Author-email: oliver.e.rayner@gmail.com
License: UNKNOWN
Project-URL: Bug Tracker, https://github.com/insert_url_here
Platform: UNKNOWN
Classifier: Programming Language :: Python :: 3
Classifier: License :: OSI Approved :: MIT License
Classifier: Operating System :: OS Independent
Requires-Python: >=3.6
License-File: LICENSE
Requires-Dist: numpy
